nashpy/__init__.py
nashpy/game.py
nashpy/algorithms/__init__.py
nashpy/algorithms/lemke_howson.py
nashpy/algorithms/lemke_howson_lex.py
nashpy/algorithms/support_enumeration.py
nashpy/algorithms/vertex_enumeration.py
nashpy/egt/__init__.py
nashpy/egt/moran_process.py
nashpy/learning/__init__.py
nashpy/learning/fictitious_play.py
nashpy/learning/imitation_dynamics.py
nashpy/learning/introspection_dynamics.py
nashpy/learning/regret_minimization.py
nashpy/learning/replicator_dynamics.py
nashpy/learning/stochastic_fictitious_play.py
nashpy/linalg/__init__.py
nashpy/linalg/minimax.py
nashpy/linalg/tableau.py
nashpy/polytope/__init__.py
nashpy/polytope/polytope.py
nashpy/repeated_games/__init__.py
nashpy/utils/__init__.py
nashpy/utils/is_best_response.py
nashpy-0.0.42.dist-info/LICENSE
nashpy-0.0.42.dist-info/WHEEL
nashpy-0.0.42.dist-info/METADATA
nashpy-0.0.42.dist-info/RECORD
