Metadata-Version: 2.1
Name: nashpy
Version: 0.0.42
Summary: A library with algorithms on 2 player games.
Home-page: https://github.com/drvinceknight/Nashpy
Author: Vince Knight, James Campbell
Author-email: vince@vknight.org
Requires-Python: >=3.10
Classifier: License :: OSI Approved :: MIT License
Requires-Dist: numpy >=1.21.0
Requires-Dist: scipy >=0.19.0
Requires-Dist: networkx >= 3.0.0
Requires-Dist: deprecated >= 1.2.14
Requires-Dist: sphinx==6.2.1 ; extra == "doc"
Requires-Dist: sphinx-rtd-theme ; extra == "doc"
Requires-Dist: sphinx-togglebutton ; extra == "doc"
Requires-Dist: matplotlib ; extra == "doc"
Requires-Dist: sphinxcontrib.mermaid ; extra == "doc"
Provides-Extra: doc
